aio_spamwatch/__init__.py
aio_spamwatch/client.py
aio_spamwatch/errors.py
aio_spamwatch/types.py
aio_spamwatch-0.0.7.dist-info/LICENSE
aio_spamwatch-0.0.7.dist-info/METADATA
aio_spamwatch-0.0.7.dist-info/WHEEL
aio_spamwatch-0.0.7.dist-info/RECORD
