Metadata-Version: 2.1
Name: aio-spamwatch
Version: 0.0.7
Summary: An asynchronous Python wrapper for the SpamWatch API.
Home-page: https://github.com/NachABR/aio-spamwatch
License: LGPLv3
Keywords: spamwatch,asynchronous,aiohttp,telegram
Author: NachABR
Author-email: nachabr@protonmail.com
Requires-Python: >=3.10,<4.0
Classifier: License :: Other/Proprietary License
Classifier: Programming Language :: Python :: 3
Classifier: Programming Language :: Python :: 3.10
Classifier: Programming Language :: Python :: 3.11
Requires-Dist: aiohttp (>=3.7)
Project-URL: Repository, https://github.com/NachABR/aio-spamwatch.git
